lumen_brain/__init__.py
lumen_brain/async_driver.py
lumen_brain/chat/__init__.py
lumen_brain/constants/__init__.py
lumen_brain/constants/endpoints.py
lumen_brain/sync_driver.py
lumen_brain/tests/driver.ipynb
lumen_brain/tools/__init__.py
lumen_brain/tools/langchain.py
lumen_brain/tools/openai.py
lumen_brain-0.3.3.dist-info/METADATA
lumen_brain-0.3.3.dist-info/WHEEL
lumen_brain-0.3.3.dist-info/RECORD
