Metadata-Version: 2.3
Name: lumen_brain
Version: 0.3.3
Summary: Operate with Lumen Brain API in Python straight forwardly
License: MIT
Author: Christian Nonis
Author-email: christiannonis@lumen-labs.ai
Requires-Python: >=3.8,<4.0
Classifier: License :: OSI Approved :: MIT License
Classifier: Programming Language :: Python :: 3
Classifier: Programming Language :: Python :: 3.8
Classifier: Programming Language :: Python :: 3.9
Classifier: Programming Language :: Python :: 3.10
Classifier: Programming Language :: Python :: 3.11
Classifier: Programming Language :: Python :: 3.12
Classifier: Programming Language :: Python :: 3.13
Requires-Dist: aiohttp (>=3.12.14,<4.0.0)
Requires-Dist: build (>=1.2.2.post1,<2.0.0)
Requires-Dist: pydantic (>=2.11.7,<3.0.0)
Requires-Dist: python-dotenv (>=1.1.1,<2.0.0)
Requires-Dist: requests (>=2.32.4,<3.0.0)
